<?xml version="1.0" encoding="utf-8"?>
<odoo>
    <!-- window_action -->
    <record id="booking_statistics_action" model="ir.actions.act_window">
        <field name="name">課程統計</field>
        <field name="type">ir.actions.act_window</field>
        <field name="res_model">booking.statistics</field>
        <field name="view_mode">tree</field>
<!--        <field name="view_id" ref="booking_statistics_tree"/>-->
        <field name="help" type="html">
            <p class="o_view_nocontent_smiling_face">
                create your first one!
            </p>
        </field>
    </record>

<!--    <record id="booking_statistics_tree" model="ir.ui.view">-->
<!--        <field name="name">booking.statistics.tree</field>-->
<!--        <field name="model">booking.statistics</field>-->
<!--        <field name="priority">1000</field>-->
<!--        <field name="arch" type="xml">-->
<!--            <tree class="o_sale_order"-->
<!--                  string="Booking Statistics"-->
<!--                  sample="1">-->
<!--                <field name="product_template_id" readonly="1"/>-->
<!--                <field name="teacher_partner_id" readonly="1"/>-->
<!--                <field name="income" readonly="1"/>-->
<!--            </tree>-->
<!--        </field>-->
<!--    </record>-->

</odoo>